{"period":"2017-08-15","raw":[{"id":24655884,"date":"2017-08-15","location":"Hagrids","players":[{"username":"","userid":0,"name":"Bill","score":0,"firstTimePlaying":true,"win":true},{"username":"","userid":0,"name":"Tom","score":0,"firstTimePlaying":true,"win":false},{"username":"","userid":0,"name":"Nick","score":0,"firstTimePlaying":true,"win":false},{"username":"","userid":0,"name":"James","score":0,"firstTimePlaying":false,"win":false},{"username":"","userid":0,"name":"Chris","score":0,"firstTimePlaying":true,"win":false}],"game":{"name":"Get Bit!","id":30539}},{"id":24655234,"date":"2017-08-15","location":"Hagrids","players":[{"username":"","userid":0,"name":"Bill","score":4,"firstTimePlaying":true,"win":false},{"username":"","userid":0,"name":"Chris","score":5,"firstTimePlaying":true,"win":true},{"username":"","userid":0,"name":"James","score":3,"firstTimePlaying":false,"win":false},{"username":"","userid":0,"name":"Nick","score":4,"firstTimePlaying":true,"win":false},{"username":"","userid":0,"name":"Tom","score":3,"firstTimePlaying":true,"win":false}],"game":{"name":"Istanbul","id":148949}},{"id":24656877,"date":"2017-08-15","location":"Hagrids","players":[{"username":"","userid":0,"name":"Tom","score":0,"firstTimePlaying":true,"win":false},{"username":"","userid":0,"name":"Bill","score":0,"firstTimePlaying":true,"win":false},{"username":"","userid":0,"name":"Nick","score":0,"firstTimePlaying":true,"win":false},{"username":"","userid":0,"name":"Chris","score":0,"firstTimePlaying":true,"win":true},{"username":"","userid":0,"name":"James","score":0,"firstTimePlaying":true,"win":false}],"game":{"name":"Poo: The Card Game","id":60579}},{"id":24657273,"date":"2017-08-15","location":"Hagrids","players":[{"username":"","userid":0,"name":"Bill","score":0,"firstTimePlaying":false,"win":true},{"username":"","userid":0,"name":"Tom","score":0,"firstTimePlaying":false,"win":false},{"username":"","userid":0,"name":"James","score":0,"firstTimePlaying":false,"win":false},{"username":"","userid":0,"name":"Chris","score":0,"firstTimePlaying":false,"win":false},{"username":"","userid":0,"name":"Nick","score":0,"firstTimePlaying":false,"win":false}],"game":{"name":"Poo: The Card Game","id":60579}}],"plays":{"playCountByGame":[["Poo: The Card Game",2],["Get Bit!",1],["Istanbul",1]],"playCountByPlayer":[["Bill",4],["Tom",4],["Nick",4],["James",4],["Chris",4]],"playerCount":[["5 Players",4]],"playCount":4,"gameCount":3,"hIndex":1,"playCountPerDayOfWeek":[["Sunday",0],["Monday",0],["Tuesday",4],["Wednesday",0],["Thursday",0],["Friday",0],["Saturday",0]],"playCountPerMonth":[["January",0],["February",0],["March",0],["April",0],["May",0],["June",0],["July",0],["August",4],["September",0],["October",0],["November",0],["December",0]],"playCountPerDay":{"2017-08-15":4}},"players":{"Bill":{"playCountByGame":[["Poo: The Card Game",2],["Get Bit!",1],["Istanbul",1]],"playerCount":[["5 Players",4]],"playCount":4,"newGameCount":3,"gameCount":3,"rivalries":[["Tom",2],["Nick",2],["James",2],["Chris",0]],"longestPlayerWinStreak":1,"longestPlayerLossStreak":2,"hIndex":1,"playCountPerDayOfWeek":[["Sunday",0],["Monday",0],["Tuesday",4],["Wednesday",0],["Thursday",0],["Friday",0],["Saturday",0]],"playCountPerMonth":[["January",0],["February",0],["March",0],["April",0],["May",0],["June",0],["July",0],["August",4],["September",0],["October",0],["November",0],["December",0]],"playCountPerDay":{"2017-08-15":4}},"Tom":{"playCountByGame":[["Poo: The Card Game",2],["Get Bit!",1],["Istanbul",1]],"playerCount":[["5 Players",4]],"playCount":4,"newGameCount":3,"gameCount":3,"rivalries":[["Nick",0],["James",0],["Bill",-2],["Chris",-2]],"longestPlayerWinStreak":0,"longestPlayerLossStreak":4,"hIndex":1,"playCountPerDayOfWeek":[["Sunday",0],["Monday",0],["Tuesday",4],["Wednesday",0],["Thursday",0],["Friday",0],["Saturday",0]],"playCountPerMonth":[["January",0],["February",0],["March",0],["April",0],["May",0],["June",0],["July",0],["August",4],["September",0],["October",0],["November",0],["December",0]],"playCountPerDay":{"2017-08-15":4}},"Nick":{"playCountByGame":[["Poo: The Card Game",2],["Get Bit!",1],["Istanbul",1]],"playerCount":[["5 Players",4]],"playCount":4,"newGameCount":3,"gameCount":3,"rivalries":[["Tom",0],["James",0],["Bill",-2],["Chris",-2]],"longestPlayerWinStreak":0,"longestPlayerLossStreak":4,"hIndex":1,"playCountPerDayOfWeek":[["Sunday",0],["Monday",0],["Tuesday",4],["Wednesday",0],["Thursday",0],["Friday",0],["Saturday",0]],"playCountPerMonth":[["January",0],["February",0],["March",0],["April",0],["May",0],["June",0],["July",0],["August",4],["September",0],["October",0],["November",0],["December",0]],"playCountPerDay":{"2017-08-15":4}},"James":{"playCountByGame":[["Poo: The Card Game",2],["Get Bit!",1],["Istanbul",1]],"playerCount":[["5 Players",4]],"playCount":4,"newGameCount":1,"gameCount":3,"rivalries":[["Tom",0],["Nick",0],["Bill",-2],["Chris",-2]],"longestPlayerWinStreak":0,"longestPlayerLossStreak":4,"hIndex":1,"playCountPerDayOfWeek":[["Sunday",0],["Monday",0],["Tuesday",4],["Wednesday",0],["Thursday",0],["Friday",0],["Saturday",0]],"playCountPerMonth":[["January",0],["February",0],["March",0],["April",0],["May",0],["June",0],["July",0],["August",4],["September",0],["October",0],["November",0],["December",0]],"playCountPerDay":{"2017-08-15":4}},"Chris":{"playCountByGame":[["Poo: The Card Game",2],["Get Bit!",1],["Istanbul",1]],"playerCount":[["5 Players",4]],"playCount":4,"newGameCount":3,"gameCount":3,"rivalries":[["Tom",2],["Nick",2],["James",2],["Bill",0]],"longestPlayerWinStreak":2,"longestPlayerLossStreak":1,"hIndex":1,"playCountPerDayOfWeek":[["Sunday",0],["Monday",0],["Tuesday",4],["Wednesday",0],["Thursday",0],["Friday",0],["Saturday",0]],"playCountPerMonth":[["January",0],["February",0],["March",0],["April",0],["May",0],["June",0],["July",0],["August",4],["September",0],["October",0],["November",0],["December",0]],"playCountPerDay":{"2017-08-15":4}}},"boardgames":{"Get Bit!":{"playerCount":[["5 Players",1]],"playCount":1,"playCountPerDayOfWeek":[["Sunday",0],["Monday",0],["Tuesday",1],["Wednesday",0],["Thursday",0],["Friday",0],["Saturday",0]],"playCountPerMonth":[["January",0],["February",0],["March",0],["April",0],["May",0],["June",0],["July",0],["August",1],["September",0],["October",0],["November",0],["December",0]],"playCountPerDay":{"2017-08-15":1}},"Istanbul":{"playerCount":[["5 Players",1]],"playCount":1,"playCountPerDayOfWeek":[["Sunday",0],["Monday",0],["Tuesday",1],["Wednesday",0],["Thursday",0],["Friday",0],["Saturday",0]],"playCountPerMonth":[["January",0],["February",0],["March",0],["April",0],["May",0],["June",0],["July",0],["August",1],["September",0],["October",0],["November",0],["December",0]],"playCountPerDay":{"2017-08-15":1}},"Poo: The Card Game":{"playerCount":[["5 Players",2]],"playCount":2,"playCountPerDayOfWeek":[["Sunday",0],["Monday",0],["Tuesday",2],["Wednesday",0],["Thursday",0],["Friday",0],["Saturday",0]],"playCountPerMonth":[["January",0],["February",0],["March",0],["April",0],["May",0],["June",0],["July",0],["August",2],["September",0],["October",0],["November",0],["December",0]],"playCountPerDay":{"2017-08-15":2}}}}