{"period":"2018-04-03","raw":[{"id":28417746,"date":"2018-04-03","location":"Home","players":[{"username":"kouphax","userid":1094472,"name":"James","score":0,"firstTimePlaying":true,"win":false},{"username":"","userid":0,"name":"Emma","score":0,"firstTimePlaying":true,"win":true}],"game":{"name":"Magic: The Gathering","id":463}},{"id":28423890,"date":"2018-04-03","location":"Home","players":[{"username":"","userid":0,"name":"Emma","score":31,"firstTimePlaying":true,"win":true},{"username":"kouphax","userid":1094472,"name":"James","score":21,"firstTimePlaying":true,"win":false}],"game":{"name":"Sagrada","id":199561}},{"id":28424295,"date":"2018-04-03","location":"Home","players":[{"username":"kouphax","userid":1094472,"name":"James","score":45,"firstTimePlaying":false,"win":true},{"username":"","userid":0,"name":"Emma","score":37,"firstTimePlaying":false,"win":false}],"game":{"name":"Sagrada","id":199561}}],"plays":{"playCountByGame":[["Sagrada",2],["Magic: The Gathering",1]],"playCountByPlayer":[["James",3],["Emma",3]],"playerCount":[["2 Players",3]],"playCount":3,"gameCount":2,"hIndex":1,"playCountPerDayOfWeek":[["Sunday",0],["Monday",0],["Tuesday",3],["Wednesday",0],["Thursday",0],["Friday",0],["Saturday",0]],"playCountPerMonth":[["January",0],["February",0],["March",0],["April",3],["May",0],["June",0],["July",0],["August",0],["September",0],["October",0],["November",0],["December",0]],"playCountPerDay":{"2018-04-03":3}},"players":{"James":{"playCountByGame":[["Sagrada",2],["Magic: The Gathering",1]],"playerCount":[["2 Players",3]],"playCount":3,"newGameCount":2,"gameCount":2,"rivalries":[["Emma",-1]],"longestPlayerWinStreak":1,"longestPlayerLossStreak":2,"hIndex":1,"playCountPerDayOfWeek":[["Sunday",0],["Monday",0],["Tuesday",3],["Wednesday",0],["Thursday",0],["Friday",0],["Saturday",0]],"playCountPerMonth":[["January",0],["February",0],["March",0],["April",3],["May",0],["June",0],["July",0],["August",0],["September",0],["October",0],["November",0],["December",0]],"playCountPerDay":{"2018-04-03":3}},"Emma":{"playCountByGame":[["Sagrada",2],["Magic: The Gathering",1]],"playerCount":[["2 Players",3]],"playCount":3,"newGameCount":2,"gameCount":2,"rivalries":[["James",1]],"longestPlayerWinStreak":2,"longestPlayerLossStreak":1,"hIndex":1,"playCountPerDayOfWeek":[["Sunday",0],["Monday",0],["Tuesday",3],["Wednesday",0],["Thursday",0],["Friday",0],["Saturday",0]],"playCountPerMonth":[["January",0],["February",0],["March",0],["April",3],["May",0],["June",0],["July",0],["August",0],["September",0],["October",0],["November",0],["December",0]],"playCountPerDay":{"2018-04-03":3}}},"boardgames":{"Magic: The Gathering":{"playerCount":[["2 Players",1]],"playCount":1,"playCountPerDayOfWeek":[["Sunday",0],["Monday",0],["Tuesday",1],["Wednesday",0],["Thursday",0],["Friday",0],["Saturday",0]],"playCountPerMonth":[["January",0],["February",0],["March",0],["April",1],["May",0],["June",0],["July",0],["August",0],["September",0],["October",0],["November",0],["December",0]],"playCountPerDay":{"2018-04-03":1}},"Sagrada":{"playerCount":[["2 Players",2]],"playCount":2,"playCountPerDayOfWeek":[["Sunday",0],["Monday",0],["Tuesday",2],["Wednesday",0],["Thursday",0],["Friday",0],["Saturday",0]],"playCountPerMonth":[["January",0],["February",0],["March",0],["April",2],["May",0],["June",0],["July",0],["August",0],["September",0],["October",0],["November",0],["December",0]],"playCountPerDay":{"2018-04-03":2}}}}