{"period":"2016-W44","raw":[{"id":20608175,"date":"2016-11-04","location":"Mum's House","players":[{"username":"","userid":0,"name":"Ollie","score":0,"firstTimePlaying":false,"win":false},{"username":"","userid":0,"name":"James","score":0,"firstTimePlaying":false,"win":true},{"username":"","userid":0,"name":"Nate","score":0,"firstTimePlaying":false,"win":false},{"username":"","userid":0,"name":"Flo","score":0,"firstTimePlaying":false,"win":false}],"game":{"name":"Zingo!","id":12616}},{"id":20608177,"date":"2016-11-04","location":"Mum's House","players":[{"username":"","userid":0,"name":"Flo","score":0,"firstTimePlaying":false,"win":false},{"username":"","userid":0,"name":"Ollie","score":0,"firstTimePlaying":false,"win":true},{"username":"","userid":0,"name":"James","score":0,"firstTimePlaying":false,"win":false},{"username":"","userid":0,"name":"Nate","score":0,"firstTimePlaying":false,"win":false}],"game":{"name":"Zingo!","id":12616}},{"id":20579012,"date":"2016-11-01","location":"Home","players":[{"username":"","userid":0,"name":"Emma","score":0,"firstTimePlaying":false,"win":false},{"username":"","userid":0,"name":"James","score":0,"firstTimePlaying":false,"win":true}],"game":{"name":"The Pursuit of Happiness","id":181687}},{"id":20579009,"date":"2016-10-31","location":"Home","players":[{"username":"","userid":0,"name":"James","score":0,"firstTimePlaying":false,"win":false}],"game":{"name":"The Pursuit of Happiness","id":181687}}],"plays":{"playCountByGame":[["Zingo!",2],["The Pursuit of Happiness",2]],"playCountByPlayer":[["James",4],["Ollie",2],["Nate",2],["Flo",2],["Emma",1]],"playerCount":[["4 Players",2],["2 Players",1],["1 Players",1]],"playCount":4,"gameCount":2,"hIndex":2,"playCountPerDayOfWeek":[["Sunday",0],["Monday",1],["Tuesday",1],["Wednesday",0],["Thursday",0],["Friday",2],["Saturday",0]],"playCountPerMonth":[["January",0],["February",0],["March",0],["April",0],["May",0],["June",0],["July",0],["August",0],["September",0],["October",1],["November",3],["December",0]],"playCountPerDay":{"2016-11-04":2,"2016-11-01":1,"2016-10-31":1}},"players":{"Ollie":{"playCountByGame":[["Zingo!",2]],"playerCount":[["4 Players",2]],"playCount":2,"newGameCount":0,"gameCount":1,"rivalries":[["Nate",1],["Flo",1],["James",0]],"longestPlayerWinStreak":1,"longestPlayerLossStreak":1,"hIndex":1,"playCountPerDayOfWeek":[["Sunday",0],["Monday",0],["Tuesday",0],["Wednesday",0],["Thursday",0],["Friday",2],["Saturday",0]],"playCountPerMonth":[["January",0],["February",0],["March",0],["April",0],["May",0],["June",0],["July",0],["August",0],["September",0],["October",0],["November",2],["December",0]],"playCountPerDay":{"2016-11-04":2}},"James":{"playCountByGame":[["Zingo!",2],["The Pursuit of Happiness",2]],"playerCount":[["4 Players",2],["2 Players",1],["1 Players",1]],"playCount":4,"newGameCount":0,"gameCount":2,"rivalries":[["Nate",1],["Flo",1],["Emma",1],["Ollie",0]],"longestPlayerWinStreak":2,"longestPlayerLossStreak":1,"hIndex":2,"playCountPerDayOfWeek":[["Sunday",0],["Monday",1],["Tuesday",1],["Wednesday",0],["Thursday",0],["Friday",2],["Saturday",0]],"playCountPerMonth":[["January",0],["February",0],["March",0],["April",0],["May",0],["June",0],["July",0],["August",0],["September",0],["October",1],["November",3],["December",0]],"playCountPerDay":{"2016-11-04":2,"2016-11-01":1,"2016-10-31":1}},"Nate":{"playCountByGame":[["Zingo!",2]],"playerCount":[["4 Players",2]],"playCount":2,"newGameCount":0,"gameCount":1,"rivalries":[["Flo",0],["Ollie",-1],["James",-1]],"longestPlayerWinStreak":0,"longestPlayerLossStreak":2,"hIndex":1,"playCountPerDayOfWeek":[["Sunday",0],["Monday",0],["Tuesday",0],["Wednesday",0],["Thursday",0],["Friday",2],["Saturday",0]],"playCountPerMonth":[["January",0],["February",0],["March",0],["April",0],["May",0],["June",0],["July",0],["August",0],["September",0],["October",0],["November",2],["December",0]],"playCountPerDay":{"2016-11-04":2}},"Flo":{"playCountByGame":[["Zingo!",2]],"playerCount":[["4 Players",2]],"playCount":2,"newGameCount":0,"gameCount":1,"rivalries":[["Nate",0],["Ollie",-1],["James",-1]],"longestPlayerWinStreak":0,"longestPlayerLossStreak":2,"hIndex":1,"playCountPerDayOfWeek":[["Sunday",0],["Monday",0],["Tuesday",0],["Wednesday",0],["Thursday",0],["Friday",2],["Saturday",0]],"playCountPerMonth":[["January",0],["February",0],["March",0],["April",0],["May",0],["June",0],["July",0],["August",0],["September",0],["October",0],["November",2],["December",0]],"playCountPerDay":{"2016-11-04":2}},"Emma":{"playCountByGame":[["The Pursuit of Happiness",1]],"playerCount":[["2 Players",1]],"playCount":1,"newGameCount":0,"gameCount":1,"rivalries":[["James",-1]],"longestPlayerWinStreak":0,"longestPlayerLossStreak":1,"hIndex":1,"playCountPerDayOfWeek":[["Sunday",0],["Monday",0],["Tuesday",1],["Wednesday",0],["Thursday",0],["Friday",0],["Saturday",0]],"playCountPerMonth":[["January",0],["February",0],["March",0],["April",0],["May",0],["June",0],["July",0],["August",0],["September",0],["October",0],["November",1],["December",0]],"playCountPerDay":{"2016-11-01":1}}},"boardgames":{"Zingo!":{"playerCount":[["4 Players",2]],"playCount":2,"playCountPerDayOfWeek":[["Sunday",0],["Monday",0],["Tuesday",0],["Wednesday",0],["Thursday",0],["Friday",2],["Saturday",0]],"playCountPerMonth":[["January",0],["February",0],["March",0],["April",0],["May",0],["June",0],["July",0],["August",0],["September",0],["October",0],["November",2],["December",0]],"playCountPerDay":{"2016-11-04":2}},"The Pursuit of Happiness":{"playerCount":[["2 Players",1],["1 Players",1]],"playCount":2,"playCountPerDayOfWeek":[["Sunday",0],["Monday",1],["Tuesday",1],["Wednesday",0],["Thursday",0],["Friday",0],["Saturday",0]],"playCountPerMonth":[["January",0],["February",0],["March",0],["April",0],["May",0],["June",0],["July",0],["August",0],["September",0],["October",1],["November",1],["December",0]],"playCountPerDay":{"2016-11-01":1,"2016-10-31":1}}}}