{"period":"2018-W12","raw":[{"id":28222347,"date":"2018-03-24","location":"Home","players":[{"username":"","userid":0,"name":"Emma","score":52,"firstTimePlaying":true,"win":true},{"username":"kouphax","userid":1094472,"name":"James","score":28,"firstTimePlaying":true,"win":false}],"game":{"name":"7 Wonders Duel","id":173346}},{"id":28208418,"date":"2018-03-23","location":"Home","players":[{"username":"kouphax","userid":1094472,"name":"James","score":0,"firstTimePlaying":false,"win":false},{"username":"","userid":0,"name":"Emma","score":0,"firstTimePlaying":false,"win":false}],"game":{"name":"Codenames Duet","id":224037}},{"id":28208521,"date":"2018-03-23","location":"Home","players":[{"username":"","userid":0,"name":"Emma","score":0,"firstTimePlaying":false,"win":false},{"username":"kouphax","userid":1094472,"name":"James","score":0,"firstTimePlaying":false,"win":false}],"game":{"name":"Codenames Duet","id":224037}},{"id":28197761,"date":"2018-03-22","location":"Home","players":[{"username":"kouphax","userid":1094472,"name":"James","score":0,"firstTimePlaying":true,"win":false},{"username":"","userid":0,"name":"Emma","score":0,"firstTimePlaying":true,"win":false}],"game":{"name":"Codenames Duet","id":224037}},{"id":28197762,"date":"2018-03-22","location":"Home","players":[{"username":"kouphax","userid":1094472,"name":"James","score":0,"firstTimePlaying":false,"win":false},{"username":"","userid":0,"name":"Emma","score":0,"firstTimePlaying":false,"win":false}],"game":{"name":"Codenames Duet","id":224037}},{"id":28198128,"date":"2018-03-22","location":"Home","players":[{"username":"kouphax","userid":1094472,"name":"James","score":0,"firstTimePlaying":false,"win":false},{"username":"","userid":0,"name":"Emma","score":0,"firstTimePlaying":false,"win":false}],"game":{"name":"Codenames Duet","id":224037}},{"id":28198188,"date":"2018-03-22","location":"Home","players":[{"username":"kouphax","userid":1094472,"name":"James","score":0,"firstTimePlaying":false,"win":false},{"username":"","userid":0,"name":"Emma","score":0,"firstTimePlaying":false,"win":false}],"game":{"name":"Codenames Duet","id":224037}}],"plays":{"playCountByGame":[["Codenames Duet",6],["7 Wonders Duel",1]],"playCountByPlayer":[["Emma",7],["James",7]],"playerCount":[["2 Players",7]],"playCount":7,"gameCount":2,"hIndex":1,"playCountPerDayOfWeek":[["Sunday",0],["Monday",0],["Tuesday",0],["Wednesday",0],["Thursday",4],["Friday",2],["Saturday",1]],"playCountPerMonth":[["January",0],["February",0],["March",7],["April",0],["May",0],["June",0],["July",0],["August",0],["September",0],["October",0],["November",0],["December",0]],"playCountPerDay":{"2018-03-24":1,"2018-03-23":2,"2018-03-22":4}},"players":{"Emma":{"playCountByGame":[["Codenames Duet",6],["7 Wonders Duel",1]],"playerCount":[["2 Players",7]],"playCount":7,"newGameCount":2,"gameCount":2,"rivalries":[["James",1]],"longestPlayerWinStreak":1,"longestPlayerLossStreak":6,"hIndex":1,"playCountPerDayOfWeek":[["Sunday",0],["Monday",0],["Tuesday",0],["Wednesday",0],["Thursday",4],["Friday",2],["Saturday",1]],"playCountPerMonth":[["January",0],["February",0],["March",7],["April",0],["May",0],["June",0],["July",0],["August",0],["September",0],["October",0],["November",0],["December",0]],"playCountPerDay":{"2018-03-24":1,"2018-03-23":2,"2018-03-22":4}},"James":{"playCountByGame":[["Codenames Duet",6],["7 Wonders Duel",1]],"playerCount":[["2 Players",7]],"playCount":7,"newGameCount":2,"gameCount":2,"rivalries":[["Emma",-1]],"longestPlayerWinStreak":0,"longestPlayerLossStreak":7,"hIndex":1,"playCountPerDayOfWeek":[["Sunday",0],["Monday",0],["Tuesday",0],["Wednesday",0],["Thursday",4],["Friday",2],["Saturday",1]],"playCountPerMonth":[["January",0],["February",0],["March",7],["April",0],["May",0],["June",0],["July",0],["August",0],["September",0],["October",0],["November",0],["December",0]],"playCountPerDay":{"2018-03-24":1,"2018-03-23":2,"2018-03-22":4}}},"boardgames":{"7 Wonders Duel":{"playerCount":[["2 Players",1]],"playCount":1,"playCountPerDayOfWeek":[["Sunday",0],["Monday",0],["Tuesday",0],["Wednesday",0],["Thursday",0],["Friday",0],["Saturday",1]],"playCountPerMonth":[["January",0],["February",0],["March",1],["April",0],["May",0],["June",0],["July",0],["August",0],["September",0],["October",0],["November",0],["December",0]],"playCountPerDay":{"2018-03-24":1}},"Codenames Duet":{"playerCount":[["2 Players",6]],"playCount":6,"playCountPerDayOfWeek":[["Sunday",0],["Monday",0],["Tuesday",0],["Wednesday",0],["Thursday",4],["Friday",2],["Saturday",0]],"playCountPerMonth":[["January",0],["February",0],["March",6],["April",0],["May",0],["June",0],["July",0],["August",0],["September",0],["October",0],["November",0],["December",0]],"playCountPerDay":{"2018-03-23":2,"2018-03-22":4}}}}